__init__.py
pyauthjwt.py
pyauthjwt-0.1.0.dist-info/LICENSE
pyauthjwt-0.1.0.dist-info/METADATA
pyauthjwt-0.1.0.dist-info/WHEEL
pyauthjwt-0.1.0.dist-info/top_level.txt
pyauthjwt-0.1.0.dist-info/RECORD
