Metadata-Version: 2.1
Name: pyauthjwt
Version: 0.1.0
Summary: Class provides mechanisms for JSON Web Token (JWT) based authentication
Author-email: "Ioannis D (devcoons)" <support@devcoons.com>
License: MIT License
Project-URL: Homepage, https://github.com/devcoons/py-auth-jwt
Project-URL: Issues, https://github.com/devcoons/py-auth-jwt/issues
Keywords: jwt,auth
Classifier: Development Status :: 5 - Production/Stable
Classifier: Intended Audience :: Developers
Classifier: Natural Language :: English
Classifier: License :: OSI Approved :: MIT License
Classifier: Operating System :: OS Independent
Classifier: Programming Language :: Python :: 3.8
Classifier: Programming Language :: Python :: 3.9
Classifier: Programming Language :: Python :: 3.10
Classifier: Programming Language :: Python :: 3.11
Classifier: Programming Language :: Python :: 3.12
Classifier: Programming Language :: Python :: Implementation :: PyPy
Requires-Python: >=3.9
License-File: LICENSE
Requires-Dist: PyJWT ==2.8.0
Provides-Extra: dev
Requires-Dist: pip-tools ; extra == 'dev'
